powermem/__init__.py
powermem/config_loader.py
powermem/configs.py
powermem/version.py
powermem/agent/__init__.py
powermem/agent/agent.py
powermem/agent/types.py
powermem/agent/abstract/__init__.py
powermem/agent/abstract/collaboration.py
powermem/agent/abstract/context.py
powermem/agent/abstract/manager.py
powermem/agent/abstract/permission.py
powermem/agent/abstract/privacy.py
powermem/agent/abstract/scope.py
powermem/agent/components/__init__.py
powermem/agent/components/collaboration_coordinator.py
powermem/agent/components/permission_controller.py
powermem/agent/components/privacy_protector.py
powermem/agent/components/scope_controller.py
powermem/agent/factories/__init__.py
powermem/agent/factories/agent_factory.py
powermem/agent/factories/config_factory.py
powermem/agent/factories/memory_factory.py
powermem/agent/implementations/__init__.py
powermem/agent/implementations/hybrid.py
powermem/agent/implementations/multi_agent.py
powermem/agent/implementations/multi_user.py
powermem/agent/wrappers/__init__.py
powermem/agent/wrappers/agent_memory_wrapper.py
powermem/agent/wrappers/compatibility_wrapper.py
powermem/core/__init__.py
powermem/core/async_memory.py
powermem/core/audit.py
powermem/core/base.py
powermem/core/memory.py
powermem/core/setup.py
powermem/core/telemetry.py
powermem/integrations/__init__.py
powermem/integrations/embeddings/__init__.py
powermem/integrations/embeddings/aws_bedrock.py
powermem/integrations/embeddings/azure_openai.py
powermem/integrations/embeddings/base.py
powermem/integrations/embeddings/configs.py
powermem/integrations/embeddings/factory.py
powermem/integrations/embeddings/gemini.py
powermem/integrations/embeddings/huggingface.py
powermem/integrations/embeddings/langchain.py
powermem/integrations/embeddings/lmstudio.py
powermem/integrations/embeddings/mock.py
powermem/integrations/embeddings/ollama.py
powermem/integrations/embeddings/openai.py
powermem/integrations/embeddings/qwen.py
powermem-0.4.0.dist-info/licenses/LICENSE
powermem-0.4.0.dist-info/METADATA
powermem-0.4.0.dist-info/WHEEL
powermem-0.4.0.dist-info/entry_points.txt
powermem-0.4.0.dist-info/top_level.txt
powermem-0.4.0.dist-info/RECORD
