Metadata-Version: 2.4
Name: powermem
Version: 0.4.0
Summary: Intelligent Memory System - Persistent memory layer for LLM applications
Author-email: powermem Team <open_oceanbase@oceanbase.com>
License: Apache-2.0
Project-URL: Homepage, https://github.com/powermem/powermem
Project-URL: Documentation, https://powermem.readthedocs.io
Project-URL: Repository, https://github.com/powermem/powermem.git
Project-URL: Issues, https://github.com/powermem/powermem/issues
Classifier: Development Status :: 3 - Alpha
Classifier: Intended Audience :: Developers
Classifier: License :: OSI Approved :: Apache Software License
Classifier: Programming Language :: Python :: 3
Classifier: Programming Language :: Python :: 3.10
Classifier: Programming Language :: Python :: 3.11
Classifier: Programming Language :: Python :: 3.12
Classifier: Topic :: Software Development :: Libraries :: Python Modules
Classifier: Topic :: Scientific/Engineering :: Artificial Intelligence
Requires-Python: >=3.10
License-File: LICENSE
Requires-Dist: pydantic>=2.0.0
Requires-Dist: pydantic-settings>=2.0.0
Requires-Dist: httpx>=0.24.0
Requires-Dist: sqlalchemy>=2.0.0
Requires-Dist: numpy>=1.21.0
Requires-Dist: pytz>=2023.3
Requires-Dist: python-dotenv>=1.0.0
Requires-Dist: fastapi>=0.100.0
Requires-Dist: uvicorn>=0.23.0
Requires-Dist: slowapi>=0.1.9
Requires-Dist: click>=8.0.0
Requires-Dist: rank-bm25>=0.2.2
Requires-Dist: pyobvector<0.3.0,>=0.2.21
Requires-Dist: jieba>=0.42.1
Requires-Dist: azure-identity>=1.24.0
Requires-Dist: psycopg2-binary>=2.9.0
Requires-Dist: pgvector>=0.2.0
Requires-Dist: psycopg>=3.2.8
Requires-Dist: psycopg-pool<4.0.0,>=3.2.6
Requires-Dist: together>=0.2.10
Requires-Dist: openai<3.0.0,>=1.90.0
Requires-Dist: anthropic>=0.7.0
Requires-Dist: ollama>=0.1.0
Requires-Dist: vertexai>=0.1.0
Requires-Dist: google-generativeai>=0.3.0
Requires-Dist: google-genai>=1.0.0
Requires-Dist: dashscope>=1.14.0
Requires-Dist: psutil>=5.9.0
Requires-Dist: zai-sdk>=0.2.0
Provides-Extra: dev
Requires-Dist: pytest>=7.0.0; extra == "dev"
Requires-Dist: pytest-asyncio>=0.21.0; extra == "dev"
Requires-Dist: pytest-cov>=4.0.0; extra == "dev"
Requires-Dist: black>=23.0.0; extra == "dev"
Requires-Dist: isort>=5.12.0; extra == "dev"
Requires-Dist: flake8>=6.0.0; extra == "dev"
Requires-Dist: mypy>=1.0.0; extra == "dev"
Provides-Extra: test
Requires-Dist: pytest>=8.2.2; extra == "test"
Requires-Dist: pytest-mock>=3.14.0; extra == "test"
Requires-Dist: pytest-asyncio>=0.23.7; extra == "test"
Requires-Dist: langchain>=1.1.0; extra == "test"
Requires-Dist: langchain-core>=1.1.0; extra == "test"
Requires-Dist: langchain-openai>=1.1.0; extra == "test"
Requires-Dist: langchain-community>=0.4.1; extra == "test"
Provides-Extra: extras
Requires-Dist: sentence-transformers>=5.0.0; extra == "extras"
Dynamic: license-file
